setup.py
apis/__init__.py
apis/redditAPI.py
examples/__init__.py
reddit_time_machine.egg-info/PKG-INFO
reddit_time_machine.egg-info/SOURCES.txt
reddit_time_machine.egg-info/dependency_links.txt
reddit_time_machine.egg-info/requires.txt
reddit_time_machine.egg-info/top_level.txt
tools/__init__.py
tools/ascii_saver.py