Metadata-Version: 1.1
Name: reddit-time-machine
Version: 0.1.0
Summary: A Python package for traveling back to a historical date and extracting reddit channel contents.
Home-page: https://github.com/sjhddh/reddit_time_machine
Author: Aaron J. Sun @sjhddh
Author-email: jhao.sun@gmail.com
License: UNKNOWN
Download-URL: https://github.com/sjhddh/reddit_time_machine/archive/0.1.tar.gz
Keywords: reddit time machine headlines download
Platform: UNKNOWN
Classifier: Development Status :: 4 - Beta
Classifier: Intended Audience :: Developers
Classifier: Topic :: Software Development :: Build Tools
Classifier: Programming Language :: Python :: 3
Classifier: Programming Language :: Python :: 3.5
